<xml xmlns="https://developers.google.com/blockly/xml" id="toolbox_oled" style="display: none">
  <category id="category_oled" name="OLED" colour="#9fa55b">
    <block type="oled_hw_i2c_init">
      <field name="ws_var" id="7{cDi=5i,Je:K72*XSvZ">sock</field>
      <field name="type">0</field>
    </block>
    <block type="oled_hw_i2c_init_pin">
      <field name="ws_var" id=")WsC}19ds4/oVCnLF6q-">sock</field>
      <field name="type">0</field>
      <field name="sda">0</field>
      <field name="scl">0</field>
    </block>
    <block type="oled_hw_spi_init">
      <field name="ws_var" id="#9SP;2{LBUVR4P?]:[v$">sock</field>
      <field name="type">0</field>
      <field name="dc">0</field>
      <field name="cs">0</field>
      <field name="res">0</field>
    </block>
    <block type="oled_hw_spi_init_pin">
      <field name="ws_var" id="#9SP;2{LBUVR4P?]:[v$">sock</field>
      <field name="type">0</field>
      <field name="sda">0</field>
      <field name="sck">0</field>
      <field name="dc">0</field>
      <field name="cs">0</field>
      <field name="res">0</field>
    </block>
    <block type="oled_draw_pixel">
      <field name="ws_var" id="MXb1j9`R7f%n5cEESyff">sock</field>
      <value name="x">
        <shadow type="math_number">
          <field name="NUM">0</field>
        </shadow>
      </value>
      <value name="y">
        <shadow type="math_number">
          <field name="NUM">0</field>
        </shadow>
      </value>
    </block>
    <block type="oled_draw_line">
      <field name="ws_var" id="0G/q|,kKMJ*wC5cf;iwE">sock</field>
      <value name="x1">
        <shadow type="math_number">
          <field name="NUM">0</field>
        </shadow>
      </value>
      <value name="y1">
        <shadow type="math_number">
          <field name="NUM">0</field>
        </shadow>
      </value>
      <value name="x2">
        <shadow type="math_number">
          <field name="NUM">0</field>
        </shadow>
      </value>
      <value name="y2">
        <shadow type="math_number">
          <field name="NUM">0</field>
        </shadow>
      </value>
    </block>
    <block type="oled_draw_frame">
      <field name="ws_var" id="lX64l2^QR5L[jW.!eS2O">sock</field>
      <value name="x">
        <shadow type="math_number">
          <field name="NUM">0</field>
        </shadow>
      </value>
      <value name="y">
        <shadow type="math_number">
          <field name="NUM">0</field>
        </shadow>
      </value>
      <value name="w">
        <shadow type="math_number">
          <field name="NUM">0</field>
        </shadow>
      </value>
      <value name="h">
        <shadow type="math_number">
          <field name="NUM">0</field>
        </shadow>
      </value>
    </block>
    <block type="oled_draw_box">
      <field name="ws_var" id="lX64l2^QR5L[jW.!eS2O">sock</field>
      <value name="x">
        <shadow type="math_number">
          <field name="NUM">0</field>
        </shadow>
      </value>
      <value name="y">
        <shadow type="math_number">
          <field name="NUM">0</field>
        </shadow>
      </value>
      <value name="w">
        <shadow type="math_number">
          <field name="NUM">0</field>
        </shadow>
      </value>
      <value name="h">
        <shadow type="math_number">
          <field name="NUM">0</field>
        </shadow>
      </value>
    </block>
    <block type="oled_draw_circle">
      <field name="ws_var" id="MXb1j9`R7f%n5cEESyff">sock</field>
      <value name="x">
        <shadow type="math_number">
          <field name="NUM">0</field>
        </shadow>
      </value>
      <value name="y">
        <shadow type="math_number">
          <field name="NUM">0</field>
        </shadow>
      </value>
      <value name="radius">
        <shadow type="math_number">
          <field name="NUM">0</field>
        </shadow>
      </value>
    </block>
    <block type="oled_draw_disc">
      <field name="ws_var" id="MXb1j9`R7f%n5cEESyff">sock</field>
      <value name="x">
        <shadow type="math_number">
          <field name="NUM">0</field>
        </shadow>
      </value>
      <value name="y">
        <shadow type="math_number">
          <field name="NUM">0</field>
        </shadow>
      </value>
      <value name="radius">
        <shadow type="math_number">
          <field name="NUM">0</field>
        </shadow>
      </value>
    </block>
    <block type="oled_set_font">
      <field name="ws_var" id="l.|#5;f/w3w=W[hIbBWL">sock</field>
      <field name="font">0</field>
    </block>
    <block type="oled_set_font_rpi">
      <field name="ws_var" id="l.|#5;f/w3w=W[hIbBWL">sock</field>
      <field name="font">0</field>
    </block>
    <block type="oled_set_cursor">
      <field name="ws_var" id="l.|#5;f/w3w=W[hIbBWL">sock</field>
      <value name="x">
        <shadow type="math_number">
          <field name="NUM">0</field>
        </shadow>
      </value>
      <value name="y">
        <shadow type="math_number">
          <field name="NUM">0</field>
        </shadow>
      </value>
    </block>
    <block type="oled_print">
      <field name="ws_var" id="l.|#5;f/w3w=W[hIbBWL">sock</field>
      <value name="str">
        <shadow type="text">
          <field name="TEXT"></field>
        </shadow>
      </value>
    </block>
    <block type="oled_send_buffer">
      <field name="ws_var" id="0G/q|,kKMJ*wC5cf;iwE">sock</field>
    </block>
    <block type="oled_clear_display">
      <field name="ws_var" id="lX64l2^QR5L[jW.!eS2O">sock</field>
    </block>
    <block type="oled_clear_buffer">
      <field name="ws_var" id="lX64l2^QR5L[jW.!eS2O">sock</field>
    </block>
  </category>
</xml>